gym_yotrading/__init__.py
gym_yotrading/datasets/__init__.py
gym_yotrading/datasets/utils.py
gym_yotrading/datasets/data/FOREX_EURUSD_1H_ASK.csv
gym_yotrading/datasets/data/STOCKS_GOOGL.csv
gym_yotrading/envs/__init__.py
gym_yotrading/envs/forex_env.py
gym_yotrading/envs/stocks_env.py
gym_yotrading/envs/trading_env.py
gym_yotrading/envs/trading_policy.py
gym_yotrading-1.0.10.dist-info/LICENSE
gym_yotrading-1.0.10.dist-info/METADATA
gym_yotrading-1.0.10.dist-info/WHEEL
gym_yotrading-1.0.10.dist-info/top_level.txt
gym_yotrading-1.0.10.dist-info/RECORD
