Metadata-Version: 2.1
Name: gym-yotrading
Version: 1.0.10
Summary: UNKNOWN
Home-page: UNKNOWN
Author: VL
Author-email: vladimir.lavrentiev@gmail.com
License: UNKNOWN
Platform: UNKNOWN
Requires-Dist: gym (>=0.12.5)
Requires-Dist: numpy (>=1.16.4)
Requires-Dist: pandas (>=0.24.2)
Requires-Dist: matplotlib (>=3.1.1)
